[
  {
    "theme": "История",
    "iconPath": "history.svg"
  },
  {
    "theme": "Математика",
    "iconPath": "math.svg"
  },
  {
    "theme": "География",
    "iconPath": "geography.svg"
  },
  {
    "theme": "Спорт",
    "iconPath": "sport.svg"
  },
  {
    "theme": "Английский язык",
    "iconPath": "english.svg"
  },
  {
    "theme": "Информатика",
    "iconPath": "informatics.svg"
  },
  {
    "theme": "Живопись",
    "iconPath": "art.svg"
  },
  {
    "theme": "Экология",
    "iconPath": "ecology.svg"
  },
  {
    "theme": "Литература",
    "iconPath": "literature.svg"
  },
  {
    "theme": "Биология",
    "iconPath": "biology.svg"

  }
]